combinatorial_peptide_pooling/.DS_Store
combinatorial_peptide_pooling/__init__.py
combinatorial_peptide_pooling/functions.py
combinatorial_peptide_pooling-0.0.31.dist-info/METADATA
combinatorial_peptide_pooling-0.0.31.dist-info/WHEEL
combinatorial_peptide_pooling-0.0.31.dist-info/licenses/LICENSE
combinatorial_peptide_pooling-0.0.31.dist-info/RECORD
