Metadata-Version: 2.1
Name: combinatorial_peptide_pooling
Version: 0.0.31
Summary: TCR deorphanization using combinatorial pooling strategy
Project-URL: Homepage, https://github.com/meyer-lab-cshl/combinatorial_pooling
Project-URL: Bug Tracker, https://github.com/meyer-lab-cshl/combinatorial_pooling/issues
Author-email: Vasilisa Kovaleva <vasilisa.kovaliova@gmail.com>
License-File: LICENSE
Classifier: License :: OSI Approved :: MIT License
Classifier: Operating System :: OS Independent
Classifier: Programming Language :: Python :: 3
Requires-Python: >=3.7
Requires-Dist: cvxpy>=1.3.2
Requires-Dist: numpy>=1.23.5
Requires-Dist: pandas>=1.5.3
Requires-Dist: trimesh>=3.23.5
